<?xml version="1.0" encoding="utf-8"?>
<jamp>
	<page id="page" title="JAMP - Grafico di Gantt" out="html" icon="../../favicon.ico" loaddata="true">
		<ds id="ds1" conn="conn6" dstable="gantt" dskey="key" />
		<div id="div1">
			<graphic id="graphic1" width="700" height="200">
				<parameter>
					<plot shadow="true" frame="true" xaxis="true" yaxis="true" />
					<title title="gantt" font="FF_FONT1,FS_BOLD" margin="3" header="GANTT_HYEAR | GANTT_HMONTH | GANTT_HDAY | GANTT_HWEEK" />
					<scale weekstyle="WEEKSTYLE_FIRSTDAYWNBR" weekfont="FF_FONT1" />
				</parameter>
			</graphic>
		</div>
		<div id="div2" style="margin: 10px">
			<dsnav id="dsnav1" dsobj="ds1" btPage="false" btNav="false" btPrint="false" />
			<gridds id="gridds1" dsobj="ds1" width="700" height="300">
				<coloumn>
					<dsselect itemlabel="Type" dsitem="type" optionvalue="ACTYPE_NORMAL,ACTYPE_MILESTONE,ACTYPE_GROUP" colwidth="150px" />
					<text itemlabel="Label" dsitem="label" minlength="1" colwidth="250px" />
					<text format="date|EN|yyyy-mm-dd|IT|dd/mm/yyyy" itemlabel="Begin" dsitem="begin" minlength="1" size="5" />
					<text format="date|EN|yyyy-mm-dd|IT|dd/mm/yyyy" itemlabel="End" dsitem="end" minlength="1" size="5" />
				</coloumn>
			</gridds>
		</div>
	</page>
</jamp>
