<?xml version="1.0" encoding="utf-8"?>
<jamp>
	<page id="page" title="JAMP - Esempio gridds collegata a una fonte XML" icon="../../favicon.ico" loaddata="true">
		<ds id="ds1" conn="conn4" scope="onelevel" dskey="key" base="/jamp/data" dslimit="10" />
		<dsnav id="dsnav1" dsobj="ds1" btNew="false" objprint="gridds1" />
		<gridds id="gridds1" dsobj="ds1" width="autosize" height="autosize">
			<coloumn>
				<text itemlabel="Citta" dsitem="citta" order="false" colwidth="150px" />
				<text itemlabel="Provincia" dsitem="provincia" order="false" colwidth="150px" />
				<text itemlabel="Regione" dsitem="regione" order="false" colwidth="150px" />
			</coloumn>
		</gridds>
	</page>
</jamp>
